gb2influxdb/__init__.py
gb2influxdb/gb2influxdb.py
gb2influxdb/version.py
gb2influxdb-0.0.1.dist-info/METADATA
gb2influxdb-0.0.1.dist-info/WHEEL
gb2influxdb-0.0.1.dist-info/entry_points.txt
gb2influxdb-0.0.1.dist-info/top_level.txt
gb2influxdb-0.0.1.dist-info/RECORD
